toytrack/__init__.py
toytrack/dataloaders.py
toytrack/detector_geometry.py
toytrack/event_generator.py
toytrack/particle_gun.py
toytrack/transforms.py
toytrack-0.1.23.dist-info/METADATA
toytrack-0.1.23.dist-info/WHEEL
toytrack-0.1.23.dist-info/top_level.txt
toytrack-0.1.23.dist-info/RECORD
