Metadata-Version: 2.1
Name: toytrack
Version: 0.1.23
Summary: A package for generating toy tracking data.
Home-page: https://github.com/murnanedaniel/ToyTrack
Author: Daniel Murnane
Author-email: daniel.thomas.murnane@cern.ch
Requires-Dist: numpy<2,>=1.0.0
Requires-Dist: pandas>=2.0.0
Requires-Dist: matplotlib>=3.8.0
Provides-Extra: torch
Requires-Dist: torch; extra == "torch"
Requires-Dist: pyyaml; extra == "torch"
